pixelforest_drf/__init__.py
pixelforest_drf/companies/__init__.py
pixelforest_drf/companies/admin.py
pixelforest_drf/companies/apps.py
pixelforest_drf/companies/models.py
pixelforest_drf/companies/migrations/0001_initial.py
pixelforest_drf/companies/migrations/__init__.py
pixelforest_drf/countries/__init__.py
pixelforest_drf/countries/admin.py
pixelforest_drf/countries/apps.py
pixelforest_drf/countries/models.py
pixelforest_drf/countries/migrations/0001_initial.py
pixelforest_drf/countries/migrations/0002_create_Countries_UNSubRegions_UNRegions.py
pixelforest_drf/countries/migrations/__init__.py
pixelforest_drf/countries/migrations_files/countries_objects.csv
pixelforest_drf/countries/migrations_files/flags.zip
pixelforest_drf/rest/__init__.py
pixelforest_drf/rest/api_urls.py
pixelforest_drf/rest/apps.py
pixelforest_drf/rest/base_api_views.py
pixelforest_drf/rest/permissions.py
pixelforest_drf/rest/companies/__init__.py
pixelforest_drf/rest/companies/api_urls.py
pixelforest_drf/rest/companies/api_views.py
pixelforest_drf/rest/companies/serializers.py
pixelforest_drf/rest/countries/__init__.py
pixelforest_drf/rest/countries/api_urls.py
pixelforest_drf/rest/countries/api_views.py
pixelforest_drf/rest/countries/serializers.py
pixelforest_drf/rest/users/__init__.py
pixelforest_drf/rest/users/api_urls.py
pixelforest_drf/rest/users/api_views.py
pixelforest_drf/rest/users/serializers.py
pixelforest_drf/users/__init__.py
pixelforest_drf/users/admin.py
pixelforest_drf/users/apps.py
pixelforest_drf/users/forms.py
pixelforest_drf/users/managers.py
pixelforest_drf/users/models.py
pixelforest_drf/users/migrations/0001_initial.py
pixelforest_drf/users/migrations/__init__.py
pixelforest_drf/utils/__init__.py
pixelforest_drf/utils/admin.py
pixelforest_drf/utils/models_mixins.py
pixelforest_drf/utils/querysets.py
pixelforest_drf-0.2.3.dist-info/LICENSE
pixelforest_drf-0.2.3.dist-info/METADATA
pixelforest_drf-0.2.3.dist-info/WHEEL
pixelforest_drf-0.2.3.dist-info/top_level.txt
pixelforest_drf-0.2.3.dist-info/RECORD
