Metadata-Version: 2.1
Name: pixelforest-drf
Version: 0.2.3
Summary: A compilation of the applications we often use in addition to Django Rest Framework
Home-page: https://bitbucket.org/pixelforest/pixelforest_drf/
Author: PixelForest Dev Team
Author-email: devteam@pixelforest.io
License: UNKNOWN
Platform: UNKNOWN
Classifier: Development Status :: 2 - Pre-Alpha
Classifier: Framework :: Django :: 2.2
Classifier: Framework :: Django :: 3.0
Classifier: Programming Language :: Python :: 3
Classifier: Programming Language :: Python :: 3.5
Classifier: Programming Language :: Python :: 3.6
Classifier: Programming Language :: Python :: 3.7
Classifier: Programming Language :: Python :: 3.8
Classifier: Programming Language :: Python :: 3 :: Only
Classifier: License :: OSI Approved :: MIT License
Classifier: Operating System :: OS Independent
Requires-Python: >=3.5
